socket_control.py
socket_control_ivie-0.0.1.dist-info/METADATA
socket_control_ivie-0.0.1.dist-info/WHEEL
socket_control_ivie-0.0.1.dist-info/top_level.txt
socket_control_ivie-0.0.1.dist-info/RECORD
